{
    "binFileName":"layer_norm_x_backprop_v2_8226818236022479353_0",
    "binFileSuffix":".o",
    "blockDim":1,
    "kernelName":"layer_norm_x_backprop_v2_8226818236022479353_0__kernel0",
    "magic":"RT_DEV_BINARY_MAGIC_ELF",
    "opParaSize":0,
    "parameters":[
        0,
        0,
        0,
        0,
        0,
        0,
        0,
        0,
        0,
        0,
        0,
        0,
        0
    ],
    "sha256":"b9c0cd6721f7af47e1cbf6ceaa4771dbce11560897786631cd235af4592f2e66",
    "workspace":{
        "num":6,
        "size":[
            8388608,
            64,
            64,
            64,
            8388608,
            8388608
        ],
        "type":[
            0,
            0,
            0,
            0,
            0,
            0
        ]
    }
}